rabbit_backup/__init__.py
rabbit_backup/rabbit_dropbox.py
rabbit_backup-0.0.6.data/scripts/rabbit-backup.py
rabbit_backup-0.0.6.dist-info/DESCRIPTION.rst
rabbit_backup-0.0.6.dist-info/METADATA
rabbit_backup-0.0.6.dist-info/RECORD
rabbit_backup-0.0.6.dist-info/WHEEL
rabbit_backup-0.0.6.dist-info/metadata.json
rabbit_backup-0.0.6.dist-info/top_level.txt
