Metadata-Version: 2.0
Name: rabbit-backup
Version: 0.0.6
Summary: backup local files to dropbox. rabbit_backup_to_dropbox will remove local/remote files after verified based on setting. 
Home-page: http://guoliang-dev.github.io/rabbit-backup
Author: Guoliang Li
Author-email: dev@liguoliang.com
License: Apache Software License
Platform: UNKNOWN
Requires-Dist: dropbox (==4.0)
Requires-Dist: python-dateutil
